pyfew/__init__.py
pyfew/features/__init__.py
pyfew/features/core.py
pyfew/features/data_utils.py
pyfew/features/sleep_feats.py
pyfew/features/feature_set/default.yaml
pyfew/features/feature_set/full.yaml
pyfew/features/feature_set/minimal.yaml
pyfew-0.0.1.dist-info/LICENSE
pyfew-0.0.1.dist-info/METADATA
pyfew-0.0.1.dist-info/WHEEL
pyfew-0.0.1.dist-info/top_level.txt
pyfew-0.0.1.dist-info/RECORD
