Metadata-Version: 2.1
Name: pyfew
Version: 0.0.1
Summary: UNKNOWN
Home-page: UNKNOWN
Author: wearables@ox
Author-email: angerhangy@gmail.com
License: MIT
Platform: UNKNOWN
License-File: LICENSE
Requires-Dist: pyyaml
Requires-Dist: catch22
Requires-Dist: numpy
Requires-Dist: scipy
